{
  "$schema": "https://mintlify.com/docs.json",
  "theme": "maple",
  "name": "Mercia's Quill Documentation",
  "colors": {
    "primary": "#c89439",
    "light": "#dbc392",
    "dark": "#c89439"
  },
  "favicon": "/favicon.ico",
  "navigation": {
    "tabs": [
      {
        "tab": "Guides",
        "groups": [
          {
            "group": "Sea of Thieves API",
            "pages": ["sea-of-thieves-api/auth", "sea-of-thieves-api/extension"]
          },
          {
            "group": "Configuration Options",
            "pages": ["config-data/gamertag-nicknames"]
          },
          {
            "group": "Error Messages",
            "pages": ["error-messages/discord-bot"]
          }
        ]
      },
      {
        "tab": "API Reference",
        "groups": [
          {
            "group": "API Documentation",
            "pages": ["api-reference/introduction"]
          },
          {
            "group": "Endpoint Examples",
            "pages": [
              "api-reference/endpoint/get",
              "api-reference/endpoint/create",
              "api-reference/endpoint/delete"
            ]
          }
        ]
      }
    ],
    "global": {
      "anchors": [
        {
          "anchor": "Main Dashboard",
          "href": "https://merciasquill.com",
          "icon": "sliders"
        },
        {
          "anchor": "Discord Application",
          "href": "https://merciasquill.com/invite",
          "icon": "code"
        },
        {
          "anchor": "Browser Extension",
          "href": "https://merciasquill.com/extension",
          "icon": "store"
        }
      ]
    }
  },
  "logo": {
    "light": "/logo/light.svg",
    "dark": "/logo/dark.svg"
  },
  "navbar": {
    "links": [
      {
        "label": "Discord Server",
        "href": "https://merciasquill.com/support"
      }
    ],
    "primary": {
      "type": "button",
      "label": "Contribute on GitHub",
      "href": "https://github.com/merciasquill/documentation"
    }
  },
  "footer": {
    "socials": {
      "discord": "https://discord.com/discovery/applications/1169623628304892045",
      "bluesky": "https://bsky.app/profile/merciasquill.com",
      "twitter": "https://x.com/MerciasQuill",
      "instagram": "https://www.instagram.com/merciasquill"
    }
  }
}
